paypalpayoutssdk/__init__.py
paypalpayoutssdk/config.py
paypalpayoutssdk/core/__init__.py
paypalpayoutssdk/core/access_token.py
paypalpayoutssdk/core/access_token_request.py
paypalpayoutssdk/core/environment.py
paypalpayoutssdk/core/paypal_http_client.py
paypalpayoutssdk/core/refresh_token_request.py
paypalpayoutssdk/core/util.py
paypalpayoutssdk/payouts/__init__.py
paypalpayoutssdk/payouts/payouts_get_request.py
paypalpayoutssdk/payouts/payouts_item_cancel_request.py
paypalpayoutssdk/payouts/payouts_item_get_request.py
paypalpayoutssdk/payouts/payouts_post_request.py
tests/payouts/__init__.py
tests/payouts/payouts_get_test.py
tests/payouts/payouts_item_cancel_test.py
tests/payouts/payouts_item_get_test.py
tests/payouts/payouts_post_test.py
paypal_payouts_sdk-1.0.0.dist-info/LICENSE
paypal_payouts_sdk-1.0.0.dist-info/METADATA
paypal_payouts_sdk-1.0.0.dist-info/WHEEL
paypal_payouts_sdk-1.0.0.dist-info/top_level.txt
paypal_payouts_sdk-1.0.0.dist-info/RECORD
